daiff/__init__.py
daiff-1.1.1.dist-info/METADATA
daiff-1.1.1.dist-info/WHEEL
daiff-1.1.1.dist-info/top_level.txt
daiff-1.1.1.dist-info/RECORD
