Metadata-Version: 2.2
Name: daiff
Version: 1.1.1
Summary: Пример пакета с зависимостями
Author: cheigg
Author-email: egorleuchin99@gmail.com
Classifier: Programming Language :: Python :: 3
Classifier: Programming Language :: Python :: 3.6
Classifier: Programming Language :: Python :: 3.7
Classifier: Programming Language :: Python :: 3.8
Classifier: Programming Language :: Python :: 3.9
Classifier: License :: OSI Approved :: MIT License
Requires-Dist: requests>=2.25.1
Requires-Dist: numpy>=1.19.5; python_version < "3.8"
Provides-Extra: dev
Requires-Dist: pytest>=6.0; extra == "dev"
